digfemig/__init__.py
digfemig/collector.py
digfemig/login.py
digfemig/main.py
digfemig-0.0.7.dist-info/METADATA
digfemig-0.0.7.dist-info/WHEEL
digfemig-0.0.7.dist-info/entry_points.txt
digfemig-0.0.7.dist-info/top_level.txt
digfemig-0.0.7.dist-info/RECORD
