Metadata-Version: 2.1
Name: digfemig
Version: 0.0.7
Summary: Utility to collect media for Instagram hashtags for the DigFemNet Project.
Author-email: Nick Ruest <ruestn@gmail.com>
Requires-Python: >=3.9.9
Requires-Dist: instagrapi
Requires-Dist: tomli
